agent_evals/__init__.py
agent_evals/cli.py
agent_evals/core.py
agent_evals/decorators.py
agent_evals/generators.py
agent_evals/judges.py
agent_evals/sandbox.py
voight-0.1.0.dist-info/METADATA
voight-0.1.0.dist-info/WHEEL
voight-0.1.0.dist-info/entry_points.txt
voight-0.1.0.dist-info/licenses/LICENSE
voight-0.1.0.dist-info/RECORD
