Metadata-Version: 2.4
Name: voight
Version: 0.1.0
Summary: The Pytest for Probabilistic Software - A testing framework for non-deterministic AI agents
Project-URL: Homepage, https://github.com/your-org/voight
Project-URL: Documentation, https://github.com/your-org/voight#readme
Project-URL: Repository, https://github.com/your-org/voight.git
Project-URL: Issues, https://github.com/your-org/voight/issues
Project-URL: Changelog, https://github.com/your-org/voight/blob/main/CHANGELOG.md
Author: Voight Contributors
License: MIT
License-File: LICENSE
Keywords: agents,ai,autogen,chatgpt,crewai,evaluation,gpt,langchain,llm,machine-learning,ml,nlp,openai,probabilistic,pytest,qa,quality-assurance,rag,retrieval-augmented-generation,testing
Classifier: Development Status :: 4 - Beta
Classifier: Intended Audience :: Developers
Classifier: License :: OSI Approved :: MIT License
Classifier: Operating System :: OS Independent
Classifier: Programming Language :: Python :: 3
Classifier: Programming Language :: Python :: 3.10
Classifier: Programming Language :: Python :: 3.11
Classifier: Programming Language :: Python :: 3.12
Classifier: Programming Language :: Python :: 3.13
Classifier: Topic :: Scientific/Engineering :: Artificial Intelligence
Classifier: Topic :: Software Development :: Quality Assurance
Classifier: Topic :: Software Development :: Testing
Classifier: Typing :: Typed
Requires-Python: >=3.10
Requires-Dist: click>=8.0.0
Requires-Dist: openai>=1.0.0
Requires-Dist: pydantic>=2.0.0
Provides-Extra: dev
Requires-Dist: pytest>=7.0.0; extra == 'dev'
Requires-Dist: ruff>=0.1.0; extra == 'dev'
